{
  "Storm League": {
    "Tomb of the Spider Queen": {
      "Abathur": {
        "wins": 0,
        "losses": 2,
        "games_played": 2,
        "win_rate": 0
      },
      "Ana": {
        "wins": 12,
        "losses": 6,
        "games_played": 18,
        "win_rate": 66.67
      },
      "Anub'arak": {
        "wins": 0,
        "losses": 1,
        "games_played": 1,
        "win_rate": 0
      },
      "Azmodan": {
        "wins": 9,
        "losses": 13,
        "games_played": 22,
        "win_rate": 40.91
      },
      "Brightwing": {
        "wins": 0,
        "losses": 5,
        "games_played": 5,
        "win_rate": 0
      },
      "Cassia": {
        "wins": 5,
        "losses": 6,
        "games_played": 11,
        "win_rate": 45.45
      },
      "Deckard": {
        "wins": 1,
        "losses": 1,
        "games_played": 2,
        "win_rate": 50
      },
      "Dehaka": {
        "wins": 2,
        "losses": 1,
        "games_played": 3,
        "win_rate": 66.67
      },
      "Diablo": {
        "wins": 0,
        "losses": 1,
        "games_played": 1,
        "win_rate": 0
      },
      "E.T.C.": {
        "wins": 0,
        "losses": 1,
        "games_played": 1,
        "win_rate": 0
      },
      "Falstad": {
        "wins": 0,
        "losses": 1,
        "games_played": 1,
        "win_rate": 0
      },
      "Fenix": {
        "wins": 0,
        "losses": 1,
        "games_played": 1,
        "win_rate": 0
      },
      "Gall": {
        "wins": 0,
        "losses": 1,
        "games_played": 1,
        "win_rate": 0
      },
      "Garrosh": {
        "wins": 7,
        "losses": 0,
        "games_played": 7,
        "win_rate": 100
      },
      "Gul'dan": {
        "wins": 1,
        "losses": 2,
        "games_played": 3,
        "win_rate": 33.33
      },
      "Illidan": {
        "wins": 1,
        "losses": 0,
        "games_played": 1,
        "win_rate": 100
      },
      "Imperius": {
        "wins": 1,
        "losses": 0,
        "games_played": 1,
        "win_rate": 100
      },
      "Junkrat": {
        "wins": 2,
        "losses": 1,
        "games_played": 3,
        "win_rate": 66.67
      },
      "Kael'thas": {
        "wins": 1,
        "losses": 0,
        "games_played": 1,
        "win_rate": 100
      },
      "Kel'Thuzad": {
        "wins": 1,
        "losses": 2,
        "games_played": 3,
        "win_rate": 33.33
      },
      "Leoric": {
        "wins": 2,
        "losses": 1,
        "games_played": 3,
        "win_rate": 66.67
      },
      "Li-Ming": {
        "wins": 1,
        "losses": 3,
        "games_played": 4,
        "win_rate": 25
      },
      "Lt. Morales": {
        "wins": 1,
        "losses": 1,
        "games_played": 2,
        "win_rate": 50
      },
      "L\u00facio": {
        "wins": 2,
        "losses": 2,
        "games_played": 4,
        "win_rate": 50
      },
      "Lunara": {
        "wins": 0,
        "losses": 1,
        "games_played": 1,
        "win_rate": 0
      },
      "Malfurion": {
        "wins": 2,
        "losses": 0,
        "games_played": 2,
        "win_rate": 100
      },
      "Medivh": {
        "wins": 0,
        "losses": 1,
        "games_played": 1,
        "win_rate": 0
      },
      "Mei": {
        "wins": 0,
        "losses": 3,
        "games_played": 3,
        "win_rate": 0
      },
      "Muradin": {
        "wins": 1,
        "losses": 2,
        "games_played": 3,
        "win_rate": 33.33
      },
      "Murky": {
        "wins": 0,
        "losses": 3,
        "games_played": 3,
        "win_rate": 0
      },
      "Nazeebo": {
        "wins": 24,
        "losses": 22,
        "games_played": 46,
        "win_rate": 52.17
      },
      "Nova": {
        "wins": 8,
        "losses": 3,
        "games_played": 11,
        "win_rate": 72.73
      },
      "Qhira": {
        "wins": 0,
        "losses": 3,
        "games_played": 3,
        "win_rate": 0
      },
      "Ragnaros": {
        "wins": 0,
        "losses": 1,
        "games_played": 1,
        "win_rate": 0
      },
      "Raynor": {
        "wins": 3,
        "losses": 5,
        "games_played": 8,
        "win_rate": 37.5
      },
      "Sgt. Hammer": {
        "wins": 1,
        "losses": 2,
        "games_played": 3,
        "win_rate": 33.33
      },
      "Stitches": {
        "wins": 6,
        "losses": 6,
        "games_played": 12,
        "win_rate": 50
      },
      "Stukov": {
        "wins": 2,
        "losses": 2,
        "games_played": 4,
        "win_rate": 50
      },
      "Tassadar": {
        "wins": 0,
        "losses": 1,
        "games_played": 1,
        "win_rate": 0
      },
      "The Butcher": {
        "wins": 0,
        "losses": 3,
        "games_played": 3,
        "win_rate": 0
      },
      "Tracer": {
        "wins": 16,
        "losses": 11,
        "games_played": 27,
        "win_rate": 59.26
      },
      "Tychus": {
        "wins": 2,
        "losses": 3,
        "games_played": 5,
        "win_rate": 40
      },
      "Valla": {
        "wins": 5,
        "losses": 4,
        "games_played": 9,
        "win_rate": 55.56
      },
      "Varian": {
        "wins": 2,
        "losses": 3,
        "games_played": 5,
        "win_rate": 40
      },
      "Xul": {
        "wins": 2,
        "losses": 1,
        "games_played": 3,
        "win_rate": 66.67
      },
      "Zeratul": {
        "wins": 1,
        "losses": 0,
        "games_played": 1,
        "win_rate": 100
      },
      "Zul'jin": {
        "wins": 1,
        "losses": 0,
        "games_played": 1,
        "win_rate": 100
      }
    },
    "Garden of Terror": {
      "Abathur": {
        "wins": 1,
        "losses": 2,
        "games_played": 3,
        "win_rate": 33.33
      },
      "Ana": {
        "wins": 6,
        "losses": 7,
        "games_played": 13,
        "win_rate": 46.15
      },
      "Anduin": {
        "wins": 0,
        "losses": 1,
        "games_played": 1,
        "win_rate": 0
      },
      "Anub'arak": {
        "wins": 0,
        "losses": 1,
        "games_played": 1,
        "win_rate": 0
      },
      "Azmodan": {
        "wins": 7,
        "losses": 10,
        "games_played": 17,
        "win_rate": 41.18
      },
      "Brightwing": {
        "wins": 1,
        "losses": 1,
        "games_played": 2,
        "win_rate": 50
      },
      "Cassia": {
        "wins": 4,
        "losses": 2,
        "games_played": 6,
        "win_rate": 66.67
      },
      "Cho": {
        "wins": 1,
        "losses": 0,
        "games_played": 1,
        "win_rate": 100
      },
      "Deckard": {
        "wins": 3,
        "losses": 2,
        "games_played": 5,
        "win_rate": 60
      },
      "Dehaka": {
        "wins": 1,
        "losses": 0,
        "games_played": 1,
        "win_rate": 100
      },
      "Diablo": {
        "wins": 1,
        "losses": 0,
        "games_played": 1,
        "win_rate": 100
      },
      "E.T.C.": {
        "wins": 1,
        "losses": 1,
        "games_played": 2,
        "win_rate": 50
      },
      "Garrosh": {
        "wins": 2,
        "losses": 3,
        "games_played": 5,
        "win_rate": 40
      },
      "Gul'dan": {
        "wins": 1,
        "losses": 1,
        "games_played": 2,
        "win_rate": 50
      },
      "Imperius": {
        "wins": 0,
        "losses": 2,
        "games_played": 2,
        "win_rate": 0
      },
      "Junkrat": {
        "wins": 1,
        "losses": 0,
        "games_played": 1,
        "win_rate": 100
      },
      "Kael'thas": {
        "wins": 1,
        "losses": 2,
        "games_played": 3,
        "win_rate": 33.33
      },
      "Kel'Thuzad": {
        "wins": 1,
        "losses": 2,
        "games_played": 3,
        "win_rate": 33.33
      },
      "Leoric": {
        "wins": 1,
        "losses": 2,
        "games_played": 3,
        "win_rate": 33.33
      },
      "Li-Ming": {
        "wins": 0,
        "losses": 2,
        "games_played": 2,
        "win_rate": 0
      },
      "L\u00facio": {
        "wins": 2,
        "losses": 5,
        "games_played": 7,
        "win_rate": 28.57
      },
      "Lunara": {
        "wins": 1,
        "losses": 0,
        "games_played": 1,
        "win_rate": 100
      },
      "Malfurion": {
        "wins": 2,
        "losses": 1,
        "games_played": 3,
        "win_rate": 66.67
      },
      "Medivh": {
        "wins": 3,
        "losses": 1,
        "games_played": 4,
        "win_rate": 75
      },
      "Mei": {
        "wins": 2,
        "losses": 0,
        "games_played": 2,
        "win_rate": 100
      },
      "Muradin": {
        "wins": 0,
        "losses": 3,
        "games_played": 3,
        "win_rate": 0
      },
      "Murky": {
        "wins": 0,
        "losses": 1,
        "games_played": 1,
        "win_rate": 0
      },
      "Nazeebo": {
        "wins": 41,
        "losses": 21,
        "games_played": 62,
        "win_rate": 66.13
      },
      "Nova": {
        "wins": 1,
        "losses": 6,
        "games_played": 7,
        "win_rate": 14.29
      },
      "Qhira": {
        "wins": 1,
        "losses": 0,
        "games_played": 1,
        "win_rate": 100
      },
      "Ragnaros": {
        "wins": 2,
        "losses": 0,
        "games_played": 2,
        "win_rate": 100
      },
      "Raynor": {
        "wins": 4,
        "losses": 0,
        "games_played": 4,
        "win_rate": 100
      },
      "Rexxar": {
        "wins": 1,
        "losses": 0,
        "games_played": 1,
        "win_rate": 100
      },
      "Stitches": {
        "wins": 5,
        "losses": 6,
        "games_played": 11,
        "win_rate": 45.45
      },
      "Stukov": {
        "wins": 1,
        "losses": 1,
        "games_played": 2,
        "win_rate": 50
      },
      "Tassadar": {
        "wins": 0,
        "losses": 1,
        "games_played": 1,
        "win_rate": 0
      },
      "The Butcher": {
        "wins": 1,
        "losses": 2,
        "games_played": 3,
        "win_rate": 33.33
      },
      "Tracer": {
        "wins": 15,
        "losses": 11,
        "games_played": 26,
        "win_rate": 57.69
      },
      "Tychus": {
        "wins": 3,
        "losses": 2,
        "games_played": 5,
        "win_rate": 60
      },
      "Valla": {
        "wins": 0,
        "losses": 2,
        "games_played": 2,
        "win_rate": 0
      },
      "Varian": {
        "wins": 3,
        "losses": 4,
        "games_played": 7,
        "win_rate": 42.86
      },
      "Xul": {
        "wins": 3,
        "losses": 0,
        "games_played": 3,
        "win_rate": 100
      },
      "Zeratul": {
        "wins": 0,
        "losses": 1,
        "games_played": 1,
        "win_rate": 0
      }
    },
    "Alterac Pass": {
      "Abathur": {
        "wins": 0,
        "losses": 1,
        "games_played": 1,
        "win_rate": 0
      },
      "Ana": {
        "wins": 13,
        "losses": 10,
        "games_played": 23,
        "win_rate": 56.52
      },
      "Anduin": {
        "wins": 0,
        "losses": 2,
        "games_played": 2,
        "win_rate": 0
      },
      "Anub'arak": {
        "wins": 1,
        "losses": 0,
        "games_played": 1,
        "win_rate": 100
      },
      "Artanis": {
        "wins": 0,
        "losses": 1,
        "games_played": 1,
        "win_rate": 0
      },
      "Azmodan": {
        "wins": 8,
        "losses": 6,
        "games_played": 14,
        "win_rate": 57.14
      },
      "Brightwing": {
        "wins": 2,
        "losses": 3,
        "games_played": 5,
        "win_rate": 40
      },
      "Cassia": {
        "wins": 2,
        "losses": 3,
        "games_played": 5,
        "win_rate": 40
      },
      "Deckard": {
        "wins": 2,
        "losses": 0,
        "games_played": 2,
        "win_rate": 100
      },
      "Dehaka": {
        "wins": 1,
        "losses": 0,
        "games_played": 1,
        "win_rate": 100
      },
      "Diablo": {
        "wins": 1,
        "losses": 2,
        "games_played": 3,
        "win_rate": 33.33
      },
      "E.T.C.": {
        "wins": 1,
        "losses": 0,
        "games_played": 1,
        "win_rate": 100
      },
      "Falstad": {
        "wins": 0,
        "losses": 2,
        "games_played": 2,
        "win_rate": 0
      },
      "Fenix": {
        "wins": 0,
        "losses": 1,
        "games_played": 1,
        "win_rate": 0
      },
      "Gall": {
        "wins": 0,
        "losses": 1,
        "games_played": 1,
        "win_rate": 0
      },
      "Garrosh": {
        "wins": 7,
        "losses": 2,
        "games_played": 9,
        "win_rate": 77.78
      },
      "Gul'dan": {
        "wins": 1,
        "losses": 0,
        "games_played": 1,
        "win_rate": 100
      },
      "Hanzo": {
        "wins": 1,
        "losses": 0,
        "games_played": 1,
        "win_rate": 100
      },
      "Illidan": {
        "wins": 3,
        "losses": 5,
        "games_played": 8,
        "win_rate": 37.5
      },
      "Johanna": {
        "wins": 0,
        "losses": 1,
        "games_played": 1,
        "win_rate": 0
      },
      "Junkrat": {
        "wins": 1,
        "losses": 2,
        "games_played": 3,
        "win_rate": 33.33
      },
      "Kael'thas": {
        "wins": 1,
        "losses": 1,
        "games_played": 2,
        "win_rate": 50
      },
      "Kel'Thuzad": {
        "wins": 2,
        "losses": 2,
        "games_played": 4,
        "win_rate": 50
      },
      "Leoric": {
        "wins": 5,
        "losses": 1,
        "games_played": 6,
        "win_rate": 83.33
      },
      "Li-Ming": {
        "wins": 3,
        "losses": 1,
        "games_played": 4,
        "win_rate": 75
      },
      "L\u00facio": {
        "wins": 1,
        "losses": 3,
        "games_played": 4,
        "win_rate": 25
      },
      "Lunara": {
        "wins": 3,
        "losses": 0,
        "games_played": 3,
        "win_rate": 100
      },
      "Malfurion": {
        "wins": 0,
        "losses": 2,
        "games_played": 2,
        "win_rate": 0
      },
      "Medivh": {
        "wins": 0,
        "losses": 2,
        "games_played": 2,
        "win_rate": 0
      },
      "Mei": {
        "wins": 2,
        "losses": 0,
        "games_played": 2,
        "win_rate": 100
      },
      "Muradin": {
        "wins": 2,
        "losses": 0,
        "games_played": 2,
        "win_rate": 100
      },
      "Murky": {
        "wins": 2,
        "losses": 2,
        "games_played": 4,
        "win_rate": 50
      },
      "Nazeebo": {
        "wins": 31,
        "losses": 27,
        "games_played": 58,
        "win_rate": 53.45
      },
      "Nova": {
        "wins": 0,
        "losses": 1,
        "games_played": 1,
        "win_rate": 0
      },
      "Qhira": {
        "wins": 1,
        "losses": 1,
        "games_played": 2,
        "win_rate": 50
      },
      "Ragnaros": {
        "wins": 0,
        "losses": 2,
        "games_played": 2,
        "win_rate": 0
      },
      "Raynor": {
        "wins": 0,
        "losses": 2,
        "games_played": 2,
        "win_rate": 0
      },
      "Rehgar": {
        "wins": 0,
        "losses": 1,
        "games_played": 1,
        "win_rate": 0
      },
      "Rexxar": {
        "wins": 0,
        "losses": 1,
        "games_played": 1,
        "win_rate": 0
      },
      "Sgt. Hammer": {
        "wins": 1,
        "losses": 1,
        "games_played": 2,
        "win_rate": 50
      },
      "Stitches": {
        "wins": 4,
        "losses": 4,
        "games_played": 8,
        "win_rate": 50
      },
      "Stukov": {
        "wins": 2,
        "losses": 3,
        "games_played": 5,
        "win_rate": 40
      },
      "Tassadar": {
        "wins": 5,
        "losses": 2,
        "games_played": 7,
        "win_rate": 71.43
      },
      "The Butcher": {
        "wins": 1,
        "losses": 1,
        "games_played": 2,
        "win_rate": 50
      },
      "Thrall": {
        "wins": 1,
        "losses": 1,
        "games_played": 2,
        "win_rate": 50
      },
      "Tracer": {
        "wins": 10,
        "losses": 11,
        "games_played": 21,
        "win_rate": 47.62
      },
      "Tychus": {
        "wins": 1,
        "losses": 1,
        "games_played": 2,
        "win_rate": 50
      },
      "Valla": {
        "wins": 3,
        "losses": 4,
        "games_played": 7,
        "win_rate": 42.86
      },
      "Varian": {
        "wins": 2,
        "losses": 2,
        "games_played": 4,
        "win_rate": 50
      },
      "Xul": {
        "wins": 1,
        "losses": 2,
        "games_played": 3,
        "win_rate": 33.33
      },
      "Zeratul": {
        "wins": 0,
        "losses": 3,
        "games_played": 3,
        "win_rate": 0
      }
    },
    "Dragon Shire": {
      "Abathur": {
        "wins": 2,
        "losses": 0,
        "games_played": 2,
        "win_rate": 100
      },
      "Ana": {
        "wins": 13,
        "losses": 7,
        "games_played": 20,
        "win_rate": 65
      },
      "Anduin": {
        "wins": 0,
        "losses": 1,
        "games_played": 1,
        "win_rate": 0
      },
      "Anub'arak": {
        "wins": 2,
        "losses": 0,
        "games_played": 2,
        "win_rate": 100
      },
      "Azmodan": {
        "wins": 5,
        "losses": 4,
        "games_played": 9,
        "win_rate": 55.56
      },
      "Blaze": {
        "wins": 1,
        "losses": 0,
        "games_played": 1,
        "win_rate": 100
      },
      "Brightwing": {
        "wins": 2,
        "losses": 0,
        "games_played": 2,
        "win_rate": 100
      },
      "Cassia": {
        "wins": 0,
        "losses": 8,
        "games_played": 8,
        "win_rate": 0
      },
      "Deckard": {
        "wins": 1,
        "losses": 2,
        "games_played": 3,
        "win_rate": 33.33
      },
      "Dehaka": {
        "wins": 1,
        "losses": 1,
        "games_played": 2,
        "win_rate": 50
      },
      "Diablo": {
        "wins": 7,
        "losses": 4,
        "games_played": 11,
        "win_rate": 63.64
      },
      "Falstad": {
        "wins": 2,
        "losses": 2,
        "games_played": 4,
        "win_rate": 50
      },
      "Fenix": {
        "wins": 0,
        "losses": 1,
        "games_played": 1,
        "win_rate": 0
      },
      "Garrosh": {
        "wins": 3,
        "losses": 2,
        "games_played": 5,
        "win_rate": 60
      },
      "Gul'dan": {
        "wins": 1,
        "losses": 6,
        "games_played": 7,
        "win_rate": 14.29
      },
      "Hanzo": {
        "wins": 0,
        "losses": 1,
        "games_played": 1,
        "win_rate": 0
      },
      "Illidan": {
        "wins": 1,
        "losses": 4,
        "games_played": 5,
        "win_rate": 20
      },
      "Imperius": {
        "wins": 3,
        "losses": 0,
        "games_played": 3,
        "win_rate": 100
      },
      "Johanna": {
        "wins": 1,
        "losses": 2,
        "games_played": 3,
        "win_rate": 33.33
      },
      "Junkrat": {
        "wins": 2,
        "losses": 6,
        "games_played": 8,
        "win_rate": 25
      },
      "Kael'thas": {
        "wins": 1,
        "losses": 1,
        "games_played": 2,
        "win_rate": 50
      },
      "Kel'Thuzad": {
        "wins": 1,
        "losses": 1,
        "games_played": 2,
        "win_rate": 50
      },
      "Leoric": {
        "wins": 2,
        "losses": 0,
        "games_played": 2,
        "win_rate": 100
      },
      "Li-Ming": {
        "wins": 8,
        "losses": 5,
        "games_played": 13,
        "win_rate": 61.54
      },
      "L\u00facio": {
        "wins": 2,
        "losses": 4,
        "games_played": 6,
        "win_rate": 33.33
      },
      "Lunara": {
        "wins": 0,
        "losses": 4,
        "games_played": 4,
        "win_rate": 0
      },
      "Malfurion": {
        "wins": 1,
        "losses": 0,
        "games_played": 1,
        "win_rate": 100
      },
      "Medivh": {
        "wins": 2,
        "losses": 2,
        "games_played": 4,
        "win_rate": 50
      },
      "Mei": {
        "wins": 1,
        "losses": 2,
        "games_played": 3,
        "win_rate": 33.33
      },
      "Muradin": {
        "wins": 0,
        "losses": 2,
        "games_played": 2,
        "win_rate": 0
      },
      "Murky": {
        "wins": 3,
        "losses": 2,
        "games_played": 5,
        "win_rate": 60
      },
      "Nazeebo": {
        "wins": 16,
        "losses": 14,
        "games_played": 30,
        "win_rate": 53.33
      },
      "Nova": {
        "wins": 2,
        "losses": 1,
        "games_played": 3,
        "win_rate": 66.67
      },
      "Qhira": {
        "wins": 1,
        "losses": 0,
        "games_played": 1,
        "win_rate": 100
      },
      "Ragnaros": {
        "wins": 0,
        "losses": 1,
        "games_played": 1,
        "win_rate": 0
      },
      "Raynor": {
        "wins": 5,
        "losses": 5,
        "games_played": 10,
        "win_rate": 50
      },
      "Rexxar": {
        "wins": 1,
        "losses": 1,
        "games_played": 2,
        "win_rate": 50
      },
      "Stitches": {
        "wins": 9,
        "losses": 13,
        "games_played": 22,
        "win_rate": 40.91
      },
      "Stukov": {
        "wins": 1,
        "losses": 2,
        "games_played": 3,
        "win_rate": 33.33
      },
      "Sylvanas": {
        "wins": 1,
        "losses": 0,
        "games_played": 1,
        "win_rate": 100
      },
      "Tassadar": {
        "wins": 2,
        "losses": 2,
        "games_played": 4,
        "win_rate": 50
      },
      "The Butcher": {
        "wins": 2,
        "losses": 3,
        "games_played": 5,
        "win_rate": 40
      },
      "Tracer": {
        "wins": 6,
        "losses": 9,
        "games_played": 15,
        "win_rate": 40
      },
      "Tychus": {
        "wins": 1,
        "losses": 6,
        "games_played": 7,
        "win_rate": 14.29
      },
      "Tyrande": {
        "wins": 0,
        "losses": 1,
        "games_played": 1,
        "win_rate": 0
      },
      "Valla": {
        "wins": 2,
        "losses": 0,
        "games_played": 2,
        "win_rate": 100
      },
      "Zul'jin": {
        "wins": 0,
        "losses": 1,
        "games_played": 1,
        "win_rate": 0
      }
    },
    "Infernal Shrines": {
      "Abathur": {
        "wins": 0,
        "losses": 1,
        "games_played": 1,
        "win_rate": 0
      },
      "Ana": {
        "wins": 6,
        "losses": 9,
        "games_played": 15,
        "win_rate": 40
      },
      "Anub'arak": {
        "wins": 1,
        "losses": 1,
        "games_played": 2,
        "win_rate": 50
      },
      "Artanis": {
        "wins": 1,
        "losses": 1,
        "games_played": 2,
        "win_rate": 50
      },
      "Azmodan": {
        "wins": 8,
        "losses": 6,
        "games_played": 14,
        "win_rate": 57.14
      },
      "Brightwing": {
        "wins": 4,
        "losses": 2,
        "games_played": 6,
        "win_rate": 66.67
      },
      "Cassia": {
        "wins": 3,
        "losses": 2,
        "games_played": 5,
        "win_rate": 60
      },
      "Deckard": {
        "wins": 4,
        "losses": 2,
        "games_played": 6,
        "win_rate": 66.67
      },
      "Dehaka": {
        "wins": 0,
        "losses": 1,
        "games_played": 1,
        "win_rate": 0
      },
      "Diablo": {
        "wins": 1,
        "losses": 3,
        "games_played": 4,
        "win_rate": 25
      },
      "E.T.C.": {
        "wins": 1,
        "losses": 1,
        "games_played": 2,
        "win_rate": 50
      },
      "Falstad": {
        "wins": 0,
        "losses": 1,
        "games_played": 1,
        "win_rate": 0
      },
      "Fenix": {
        "wins": 0,
        "losses": 2,
        "games_played": 2,
        "win_rate": 0
      },
      "Gall": {
        "wins": 0,
        "losses": 2,
        "games_played": 2,
        "win_rate": 0
      },
      "Garrosh": {
        "wins": 5,
        "losses": 4,
        "games_played": 9,
        "win_rate": 55.56
      },
      "Greymane": {
        "wins": 1,
        "losses": 0,
        "games_played": 1,
        "win_rate": 100
      },
      "Gul'dan": {
        "wins": 3,
        "losses": 1,
        "games_played": 4,
        "win_rate": 75
      },
      "Hanzo": {
        "wins": 0,
        "losses": 1,
        "games_played": 1,
        "win_rate": 0
      },
      "Illidan": {
        "wins": 0,
        "losses": 1,
        "games_played": 1,
        "win_rate": 0
      },
      "Jaina": {
        "wins": 1,
        "losses": 1,
        "games_played": 2,
        "win_rate": 50
      },
      "Junkrat": {
        "wins": 1,
        "losses": 2,
        "games_played": 3,
        "win_rate": 33.33
      },
      "Kael'thas": {
        "wins": 1,
        "losses": 0,
        "games_played": 1,
        "win_rate": 100
      },
      "Kel'Thuzad": {
        "wins": 3,
        "losses": 1,
        "games_played": 4,
        "win_rate": 75
      },
      "Kharazim": {
        "wins": 1,
        "losses": 0,
        "games_played": 1,
        "win_rate": 100
      },
      "Leoric": {
        "wins": 0,
        "losses": 1,
        "games_played": 1,
        "win_rate": 0
      },
      "Li-Ming": {
        "wins": 5,
        "losses": 3,
        "games_played": 8,
        "win_rate": 62.5
      },
      "Lt. Morales": {
        "wins": 1,
        "losses": 0,
        "games_played": 1,
        "win_rate": 100
      },
      "L\u00facio": {
        "wins": 1,
        "losses": 6,
        "games_played": 7,
        "win_rate": 14.29
      },
      "Lunara": {
        "wins": 3,
        "losses": 3,
        "games_played": 6,
        "win_rate": 50
      },
      "Medivh": {
        "wins": 1,
        "losses": 2,
        "games_played": 3,
        "win_rate": 33.33
      },
      "Muradin": {
        "wins": 1,
        "losses": 0,
        "games_played": 1,
        "win_rate": 100
      },
      "Murky": {
        "wins": 0,
        "losses": 4,
        "games_played": 4,
        "win_rate": 0
      },
      "Nazeebo": {
        "wins": 35,
        "losses": 14,
        "games_played": 49,
        "win_rate": 71.43
      },
      "Nova": {
        "wins": 2,
        "losses": 3,
        "games_played": 5,
        "win_rate": 40
      },
      "Qhira": {
        "wins": 0,
        "losses": 1,
        "games_played": 1,
        "win_rate": 0
      },
      "Raynor": {
        "wins": 4,
        "losses": 3,
        "games_played": 7,
        "win_rate": 57.14
      },
      "Rexxar": {
        "wins": 0,
        "losses": 1,
        "games_played": 1,
        "win_rate": 0
      },
      "Sgt. Hammer": {
        "wins": 2,
        "losses": 3,
        "games_played": 5,
        "win_rate": 40
      },
      "Stitches": {
        "wins": 6,
        "losses": 3,
        "games_played": 9,
        "win_rate": 66.67
      },
      "Stukov": {
        "wins": 1,
        "losses": 0,
        "games_played": 1,
        "win_rate": 100
      },
      "Tassadar": {
        "wins": 3,
        "losses": 3,
        "games_played": 6,
        "win_rate": 50
      },
      "The Butcher": {
        "wins": 5,
        "losses": 3,
        "games_played": 8,
        "win_rate": 62.5
      },
      "Tracer": {
        "wins": 15,
        "losses": 8,
        "games_played": 23,
        "win_rate": 65.22
      },
      "Tychus": {
        "wins": 2,
        "losses": 1,
        "games_played": 3,
        "win_rate": 66.67
      },
      "Valla": {
        "wins": 2,
        "losses": 1,
        "games_played": 3,
        "win_rate": 66.67
      },
      "Varian": {
        "wins": 0,
        "losses": 1,
        "games_played": 1,
        "win_rate": 0
      },
      "Xul": {
        "wins": 1,
        "losses": 2,
        "games_played": 3,
        "win_rate": 33.33
      },
      "Zeratul": {
        "wins": 1,
        "losses": 4,
        "games_played": 5,
        "win_rate": 20
      },
      "Zul'jin": {
        "wins": 1,
        "losses": 0,
        "games_played": 1,
        "win_rate": 100
      }
    },
    "Sky Temple": {
      "Abathur": {
        "wins": 0,
        "losses": 1,
        "games_played": 1,
        "win_rate": 0
      },
      "Ana": {
        "wins": 2,
        "losses": 2,
        "games_played": 4,
        "win_rate": 50
      },
      "Anub'arak": {
        "wins": 0,
        "losses": 1,
        "games_played": 1,
        "win_rate": 0
      },
      "Azmodan": {
        "wins": 10,
        "losses": 9,
        "games_played": 19,
        "win_rate": 52.63
      },
      "Brightwing": {
        "wins": 1,
        "losses": 1,
        "games_played": 2,
        "win_rate": 50
      },
      "Cassia": {
        "wins": 5,
        "losses": 4,
        "games_played": 9,
        "win_rate": 55.56
      },
      "Chen": {
        "wins": 0,
        "losses": 1,
        "games_played": 1,
        "win_rate": 0
      },
      "Cho": {
        "wins": 0,
        "losses": 1,
        "games_played": 1,
        "win_rate": 0
      },
      "Deckard": {
        "wins": 0,
        "losses": 2,
        "games_played": 2,
        "win_rate": 0
      },
      "Dehaka": {
        "wins": 1,
        "losses": 2,
        "games_played": 3,
        "win_rate": 33.33
      },
      "Diablo": {
        "wins": 2,
        "losses": 2,
        "games_played": 4,
        "win_rate": 50
      },
      "E.T.C.": {
        "wins": 1,
        "losses": 0,
        "games_played": 1,
        "win_rate": 100
      },
      "Falstad": {
        "wins": 2,
        "losses": 1,
        "games_played": 3,
        "win_rate": 66.67
      },
      "Fenix": {
        "wins": 0,
        "losses": 1,
        "games_played": 1,
        "win_rate": 0
      },
      "Garrosh": {
        "wins": 7,
        "losses": 5,
        "games_played": 12,
        "win_rate": 58.33
      },
      "Gazlowe": {
        "wins": 1,
        "losses": 0,
        "games_played": 1,
        "win_rate": 100
      },
      "Gul'dan": {
        "wins": 1,
        "losses": 2,
        "games_played": 3,
        "win_rate": 33.33
      },
      "Hanzo": {
        "wins": 0,
        "losses": 1,
        "games_played": 1,
        "win_rate": 0
      },
      "Illidan": {
        "wins": 1,
        "losses": 3,
        "games_played": 4,
        "win_rate": 25
      },
      "Junkrat": {
        "wins": 1,
        "losses": 1,
        "games_played": 2,
        "win_rate": 50
      },
      "Kael'thas": {
        "wins": 3,
        "losses": 5,
        "games_played": 8,
        "win_rate": 37.5
      },
      "Kel'Thuzad": {
        "wins": 1,
        "losses": 0,
        "games_played": 1,
        "win_rate": 100
      },
      "Kerrigan": {
        "wins": 0,
        "losses": 1,
        "games_played": 1,
        "win_rate": 0
      },
      "Leoric": {
        "wins": 4,
        "losses": 3,
        "games_played": 7,
        "win_rate": 57.14
      },
      "Li Li": {
        "wins": 1,
        "losses": 1,
        "games_played": 2,
        "win_rate": 50
      },
      "Li-Ming": {
        "wins": 3,
        "losses": 7,
        "games_played": 10,
        "win_rate": 30
      },
      "L\u00facio": {
        "wins": 0,
        "losses": 3,
        "games_played": 3,
        "win_rate": 0
      },
      "Lunara": {
        "wins": 1,
        "losses": 0,
        "games_played": 1,
        "win_rate": 100
      },
      "Malfurion": {
        "wins": 0,
        "losses": 2,
        "games_played": 2,
        "win_rate": 0
      },
      "Medivh": {
        "wins": 2,
        "losses": 2,
        "games_played": 4,
        "win_rate": 50
      },
      "Mei": {
        "wins": 5,
        "losses": 4,
        "games_played": 9,
        "win_rate": 55.56
      },
      "Muradin": {
        "wins": 1,
        "losses": 4,
        "games_played": 5,
        "win_rate": 20
      },
      "Murky": {
        "wins": 0,
        "losses": 2,
        "games_played": 2,
        "win_rate": 0
      },
      "Nazeebo": {
        "wins": 26,
        "losses": 14,
        "games_played": 40,
        "win_rate": 65
      },
      "Nova": {
        "wins": 7,
        "losses": 6,
        "games_played": 13,
        "win_rate": 53.85
      },
      "Qhira": {
        "wins": 0,
        "losses": 2,
        "games_played": 2,
        "win_rate": 0
      },
      "Ragnaros": {
        "wins": 1,
        "losses": 1,
        "games_played": 2,
        "win_rate": 50
      },
      "Raynor": {
        "wins": 3,
        "losses": 2,
        "games_played": 5,
        "win_rate": 60
      },
      "Rexxar": {
        "wins": 1,
        "losses": 0,
        "games_played": 1,
        "win_rate": 100
      },
      "Sgt. Hammer": {
        "wins": 1,
        "losses": 1,
        "games_played": 2,
        "win_rate": 50
      },
      "Stitches": {
        "wins": 4,
        "losses": 11,
        "games_played": 15,
        "win_rate": 26.67
      },
      "Stukov": {
        "wins": 1,
        "losses": 4,
        "games_played": 5,
        "win_rate": 20
      },
      "Sylvanas": {
        "wins": 1,
        "losses": 0,
        "games_played": 1,
        "win_rate": 100
      },
      "Tassadar": {
        "wins": 2,
        "losses": 0,
        "games_played": 2,
        "win_rate": 100
      },
      "The Butcher": {
        "wins": 2,
        "losses": 2,
        "games_played": 4,
        "win_rate": 50
      },
      "Tracer": {
        "wins": 9,
        "losses": 9,
        "games_played": 18,
        "win_rate": 50
      },
      "Tychus": {
        "wins": 2,
        "losses": 0,
        "games_played": 2,
        "win_rate": 100
      },
      "Tyrande": {
        "wins": 1,
        "losses": 0,
        "games_played": 1,
        "win_rate": 100
      },
      "Valla": {
        "wins": 4,
        "losses": 1,
        "games_played": 5,
        "win_rate": 80
      },
      "Varian": {
        "wins": 1,
        "losses": 2,
        "games_played": 3,
        "win_rate": 33.33
      },
      "Xul": {
        "wins": 2,
        "losses": 2,
        "games_played": 4,
        "win_rate": 50
      },
      "Zeratul": {
        "wins": 3,
        "losses": 1,
        "games_played": 4,
        "win_rate": 75
      },
      "Zul'jin": {
        "wins": 1,
        "losses": 1,
        "games_played": 2,
        "win_rate": 50
      }
    },
    "Cursed Hollow": {
      "Alarak": {
        "wins": 0,
        "losses": 1,
        "games_played": 1,
        "win_rate": 0
      },
      "Ana": {
        "wins": 5,
        "losses": 4,
        "games_played": 9,
        "win_rate": 55.56
      },
      "Artanis": {
        "wins": 1,
        "losses": 1,
        "games_played": 2,
        "win_rate": 50
      },
      "Auriel": {
        "wins": 0,
        "losses": 1,
        "games_played": 1,
        "win_rate": 0
      },
      "Azmodan": {
        "wins": 14,
        "losses": 10,
        "games_played": 24,
        "win_rate": 58.33
      },
      "Brightwing": {
        "wins": 1,
        "losses": 2,
        "games_played": 3,
        "win_rate": 33.33
      },
      "Cassia": {
        "wins": 6,
        "losses": 4,
        "games_played": 10,
        "win_rate": 60
      },
      "Deckard": {
        "wins": 4,
        "losses": 1,
        "games_played": 5,
        "win_rate": 80
      },
      "Dehaka": {
        "wins": 1,
        "losses": 2,
        "games_played": 3,
        "win_rate": 33.33
      },
      "Diablo": {
        "wins": 4,
        "losses": 1,
        "games_played": 5,
        "win_rate": 80
      },
      "E.T.C.": {
        "wins": 0,
        "losses": 2,
        "games_played": 2,
        "win_rate": 0
      },
      "Falstad": {
        "wins": 0,
        "losses": 3,
        "games_played": 3,
        "win_rate": 0
      },
      "Fenix": {
        "wins": 0,
        "losses": 1,
        "games_played": 1,
        "win_rate": 0
      },
      "Garrosh": {
        "wins": 3,
        "losses": 5,
        "games_played": 8,
        "win_rate": 37.5
      },
      "Gul'dan": {
        "wins": 1,
        "losses": 2,
        "games_played": 3,
        "win_rate": 33.33
      },
      "Illidan": {
        "wins": 1,
        "losses": 0,
        "games_played": 1,
        "win_rate": 100
      },
      "Junkrat": {
        "wins": 1,
        "losses": 0,
        "games_played": 1,
        "win_rate": 100
      },
      "Kael'thas": {
        "wins": 1,
        "losses": 0,
        "games_played": 1,
        "win_rate": 100
      },
      "Kel'Thuzad": {
        "wins": 0,
        "losses": 1,
        "games_played": 1,
        "win_rate": 0
      },
      "Leoric": {
        "wins": 0,
        "losses": 2,
        "games_played": 2,
        "win_rate": 0
      },
      "Li Li": {
        "wins": 0,
        "losses": 1,
        "games_played": 1,
        "win_rate": 0
      },
      "Li-Ming": {
        "wins": 7,
        "losses": 2,
        "games_played": 9,
        "win_rate": 77.78
      },
      "L\u00facio": {
        "wins": 5,
        "losses": 4,
        "games_played": 9,
        "win_rate": 55.56
      },
      "Lunara": {
        "wins": 3,
        "losses": 1,
        "games_played": 4,
        "win_rate": 75
      },
      "Malfurion": {
        "wins": 0,
        "losses": 2,
        "games_played": 2,
        "win_rate": 0
      },
      "Medivh": {
        "wins": 0,
        "losses": 4,
        "games_played": 4,
        "win_rate": 0
      },
      "Mei": {
        "wins": 2,
        "losses": 1,
        "games_played": 3,
        "win_rate": 66.67
      },
      "Muradin": {
        "wins": 2,
        "losses": 1,
        "games_played": 3,
        "win_rate": 66.67
      },
      "Murky": {
        "wins": 1,
        "losses": 2,
        "games_played": 3,
        "win_rate": 33.33
      },
      "Nazeebo": {
        "wins": 30,
        "losses": 25,
        "games_played": 55,
        "win_rate": 54.55
      },
      "Nova": {
        "wins": 2,
        "losses": 3,
        "games_played": 5,
        "win_rate": 40
      },
      "Qhira": {
        "wins": 1,
        "losses": 1,
        "games_played": 2,
        "win_rate": 50
      },
      "Raynor": {
        "wins": 2,
        "losses": 3,
        "games_played": 5,
        "win_rate": 40
      },
      "Sgt. Hammer": {
        "wins": 0,
        "losses": 1,
        "games_played": 1,
        "win_rate": 0
      },
      "Stitches": {
        "wins": 3,
        "losses": 8,
        "games_played": 11,
        "win_rate": 27.27
      },
      "Stukov": {
        "wins": 4,
        "losses": 1,
        "games_played": 5,
        "win_rate": 80
      },
      "Tassadar": {
        "wins": 1,
        "losses": 2,
        "games_played": 3,
        "win_rate": 33.33
      },
      "The Butcher": {
        "wins": 2,
        "losses": 2,
        "games_played": 4,
        "win_rate": 50
      },
      "Tracer": {
        "wins": 15,
        "losses": 10,
        "games_played": 25,
        "win_rate": 60
      },
      "Tychus": {
        "wins": 3,
        "losses": 0,
        "games_played": 3,
        "win_rate": 100
      },
      "Valla": {
        "wins": 3,
        "losses": 0,
        "games_played": 3,
        "win_rate": 100
      },
      "Varian": {
        "wins": 0,
        "losses": 2,
        "games_played": 2,
        "win_rate": 0
      },
      "Xul": {
        "wins": 2,
        "losses": 1,
        "games_played": 3,
        "win_rate": 66.67
      },
      "Zeratul": {
        "wins": 0,
        "losses": 1,
        "games_played": 1,
        "win_rate": 0
      },
      "Zul'jin": {
        "wins": 1,
        "losses": 1,
        "games_played": 2,
        "win_rate": 50
      }
    },
    "Battlefield of Eternity": {
      "Ana": {
        "wins": 2,
        "losses": 7,
        "games_played": 9,
        "win_rate": 22.22
      },
      "Anduin": {
        "wins": 0,
        "losses": 1,
        "games_played": 1,
        "win_rate": 0
      },
      "Anub'arak": {
        "wins": 3,
        "losses": 1,
        "games_played": 4,
        "win_rate": 75
      },
      "Azmodan": {
        "wins": 18,
        "losses": 19,
        "games_played": 37,
        "win_rate": 48.65
      },
      "Brightwing": {
        "wins": 2,
        "losses": 0,
        "games_played": 2,
        "win_rate": 100
      },
      "Cassia": {
        "wins": 4,
        "losses": 2,
        "games_played": 6,
        "win_rate": 66.67
      },
      "Deckard": {
        "wins": 1,
        "losses": 1,
        "games_played": 2,
        "win_rate": 50
      },
      "Dehaka": {
        "wins": 1,
        "losses": 1,
        "games_played": 2,
        "win_rate": 50
      },
      "Diablo": {
        "wins": 0,
        "losses": 1,
        "games_played": 1,
        "win_rate": 0
      },
      "E.T.C.": {
        "wins": 1,
        "losses": 0,
        "games_played": 1,
        "win_rate": 100
      },
      "Falstad": {
        "wins": 3,
        "losses": 1,
        "games_played": 4,
        "win_rate": 75
      },
      "Gall": {
        "wins": 1,
        "losses": 0,
        "games_played": 1,
        "win_rate": 100
      },
      "Garrosh": {
        "wins": 10,
        "losses": 7,
        "games_played": 17,
        "win_rate": 58.82
      },
      "Gul'dan": {
        "wins": 2,
        "losses": 3,
        "games_played": 5,
        "win_rate": 40
      },
      "Illidan": {
        "wins": 1,
        "losses": 0,
        "games_played": 1,
        "win_rate": 100
      },
      "Jaina": {
        "wins": 0,
        "losses": 1,
        "games_played": 1,
        "win_rate": 0
      },
      "Johanna": {
        "wins": 0,
        "losses": 1,
        "games_played": 1,
        "win_rate": 0
      },
      "Junkrat": {
        "wins": 1,
        "losses": 0,
        "games_played": 1,
        "win_rate": 100
      },
      "Kael'thas": {
        "wins": 8,
        "losses": 13,
        "games_played": 21,
        "win_rate": 38.1
      },
      "Kel'Thuzad": {
        "wins": 1,
        "losses": 2,
        "games_played": 3,
        "win_rate": 33.33
      },
      "Leoric": {
        "wins": 0,
        "losses": 1,
        "games_played": 1,
        "win_rate": 0
      },
      "Li Li": {
        "wins": 1,
        "losses": 0,
        "games_played": 1,
        "win_rate": 100
      },
      "Li-Ming": {
        "wins": 8,
        "losses": 7,
        "games_played": 15,
        "win_rate": 53.33
      },
      "L\u00facio": {
        "wins": 2,
        "losses": 1,
        "games_played": 3,
        "win_rate": 66.67
      },
      "Malfurion": {
        "wins": 1,
        "losses": 2,
        "games_played": 3,
        "win_rate": 33.33
      },
      "Medivh": {
        "wins": 1,
        "losses": 1,
        "games_played": 2,
        "win_rate": 50
      },
      "Mei": {
        "wins": 2,
        "losses": 0,
        "games_played": 2,
        "win_rate": 100
      },
      "Muradin": {
        "wins": 6,
        "losses": 1,
        "games_played": 7,
        "win_rate": 85.71
      },
      "Murky": {
        "wins": 0,
        "losses": 1,
        "games_played": 1,
        "win_rate": 0
      },
      "Nazeebo": {
        "wins": 8,
        "losses": 13,
        "games_played": 21,
        "win_rate": 38.1
      },
      "Nova": {
        "wins": 0,
        "losses": 1,
        "games_played": 1,
        "win_rate": 0
      },
      "Qhira": {
        "wins": 0,
        "losses": 1,
        "games_played": 1,
        "win_rate": 0
      },
      "Raynor": {
        "wins": 5,
        "losses": 2,
        "games_played": 7,
        "win_rate": 71.43
      },
      "Rexxar": {
        "wins": 1,
        "losses": 1,
        "games_played": 2,
        "win_rate": 50
      },
      "Sgt. Hammer": {
        "wins": 3,
        "losses": 1,
        "games_played": 4,
        "win_rate": 75
      },
      "Stitches": {
        "wins": 11,
        "losses": 7,
        "games_played": 18,
        "win_rate": 61.11
      },
      "Stukov": {
        "wins": 4,
        "losses": 4,
        "games_played": 8,
        "win_rate": 50
      },
      "Tassadar": {
        "wins": 0,
        "losses": 1,
        "games_played": 1,
        "win_rate": 0
      },
      "The Butcher": {
        "wins": 0,
        "losses": 2,
        "games_played": 2,
        "win_rate": 0
      },
      "Tracer": {
        "wins": 0,
        "losses": 3,
        "games_played": 3,
        "win_rate": 0
      },
      "Tychus": {
        "wins": 4,
        "losses": 1,
        "games_played": 5,
        "win_rate": 80
      },
      "Valla": {
        "wins": 3,
        "losses": 4,
        "games_played": 7,
        "win_rate": 42.86
      },
      "Varian": {
        "wins": 3,
        "losses": 4,
        "games_played": 7,
        "win_rate": 42.86
      },
      "Zul'jin": {
        "wins": 1,
        "losses": 6,
        "games_played": 7,
        "win_rate": 14.29
      }
    },
    "Volskaya Foundry": {
      "Ana": {
        "wins": 6,
        "losses": 8,
        "games_played": 14,
        "win_rate": 42.86
      },
      "Anduin": {
        "wins": 0,
        "losses": 2,
        "games_played": 2,
        "win_rate": 0
      },
      "Anub'arak": {
        "wins": 2,
        "losses": 1,
        "games_played": 3,
        "win_rate": 66.67
      },
      "Artanis": {
        "wins": 0,
        "losses": 1,
        "games_played": 1,
        "win_rate": 0
      },
      "Azmodan": {
        "wins": 5,
        "losses": 3,
        "games_played": 8,
        "win_rate": 62.5
      },
      "Brightwing": {
        "wins": 2,
        "losses": 1,
        "games_played": 3,
        "win_rate": 66.67
      },
      "Cassia": {
        "wins": 3,
        "losses": 1,
        "games_played": 4,
        "win_rate": 75
      },
      "Chen": {
        "wins": 1,
        "losses": 0,
        "games_played": 1,
        "win_rate": 100
      },
      "Deckard": {
        "wins": 2,
        "losses": 3,
        "games_played": 5,
        "win_rate": 40
      },
      "Diablo": {
        "wins": 2,
        "losses": 4,
        "games_played": 6,
        "win_rate": 33.33
      },
      "E.T.C.": {
        "wins": 0,
        "losses": 2,
        "games_played": 2,
        "win_rate": 0
      },
      "Falstad": {
        "wins": 0,
        "losses": 1,
        "games_played": 1,
        "win_rate": 0
      },
      "Garrosh": {
        "wins": 1,
        "losses": 4,
        "games_played": 5,
        "win_rate": 20
      },
      "Greymane": {
        "wins": 1,
        "losses": 0,
        "games_played": 1,
        "win_rate": 100
      },
      "Gul'dan": {
        "wins": 1,
        "losses": 0,
        "games_played": 1,
        "win_rate": 100
      },
      "Hanzo": {
        "wins": 0,
        "losses": 1,
        "games_played": 1,
        "win_rate": 0
      },
      "Johanna": {
        "wins": 1,
        "losses": 0,
        "games_played": 1,
        "win_rate": 100
      },
      "Junkrat": {
        "wins": 3,
        "losses": 4,
        "games_played": 7,
        "win_rate": 42.86
      },
      "Kael'thas": {
        "wins": 2,
        "losses": 4,
        "games_played": 6,
        "win_rate": 33.33
      },
      "Kel'Thuzad": {
        "wins": 0,
        "losses": 2,
        "games_played": 2,
        "win_rate": 0
      },
      "Leoric": {
        "wins": 2,
        "losses": 0,
        "games_played": 2,
        "win_rate": 100
      },
      "Li Li": {
        "wins": 1,
        "losses": 0,
        "games_played": 1,
        "win_rate": 100
      },
      "Li-Ming": {
        "wins": 8,
        "losses": 5,
        "games_played": 13,
        "win_rate": 61.54
      },
      "L\u00facio": {
        "wins": 0,
        "losses": 1,
        "games_played": 1,
        "win_rate": 0
      },
      "Malfurion": {
        "wins": 1,
        "losses": 0,
        "games_played": 1,
        "win_rate": 100
      },
      "Muradin": {
        "wins": 1,
        "losses": 0,
        "games_played": 1,
        "win_rate": 100
      },
      "Murky": {
        "wins": 1,
        "losses": 0,
        "games_played": 1,
        "win_rate": 100
      },
      "Nazeebo": {
        "wins": 5,
        "losses": 6,
        "games_played": 11,
        "win_rate": 45.45
      },
      "Nova": {
        "wins": 3,
        "losses": 1,
        "games_played": 4,
        "win_rate": 75
      },
      "Qhira": {
        "wins": 0,
        "losses": 1,
        "games_played": 1,
        "win_rate": 0
      },
      "Ragnaros": {
        "wins": 3,
        "losses": 0,
        "games_played": 3,
        "win_rate": 100
      },
      "Raynor": {
        "wins": 1,
        "losses": 1,
        "games_played": 2,
        "win_rate": 50
      },
      "Sgt. Hammer": {
        "wins": 0,
        "losses": 1,
        "games_played": 1,
        "win_rate": 0
      },
      "Stitches": {
        "wins": 4,
        "losses": 4,
        "games_played": 8,
        "win_rate": 50
      },
      "Stukov": {
        "wins": 0,
        "losses": 1,
        "games_played": 1,
        "win_rate": 0
      },
      "Tassadar": {
        "wins": 0,
        "losses": 1,
        "games_played": 1,
        "win_rate": 0
      },
      "The Butcher": {
        "wins": 1,
        "losses": 0,
        "games_played": 1,
        "win_rate": 100
      },
      "Tracer": {
        "wins": 10,
        "losses": 5,
        "games_played": 15,
        "win_rate": 66.67
      },
      "Tyrande": {
        "wins": 2,
        "losses": 0,
        "games_played": 2,
        "win_rate": 100
      },
      "Valla": {
        "wins": 3,
        "losses": 4,
        "games_played": 7,
        "win_rate": 42.86
      },
      "Varian": {
        "wins": 0,
        "losses": 1,
        "games_played": 1,
        "win_rate": 0
      },
      "Zeratul": {
        "wins": 1,
        "losses": 0,
        "games_played": 1,
        "win_rate": 100
      },
      "Zul'jin": {
        "wins": 1,
        "losses": 1,
        "games_played": 2,
        "win_rate": 50
      }
    },
    "Braxis Holdout": {
      "Ana": {
        "wins": 11,
        "losses": 5,
        "games_played": 16,
        "win_rate": 68.75
      },
      "Anub'arak": {
        "wins": 0,
        "losses": 2,
        "games_played": 2,
        "win_rate": 0
      },
      "Artanis": {
        "wins": 0,
        "losses": 1,
        "games_played": 1,
        "win_rate": 0
      },
      "Azmodan": {
        "wins": 30,
        "losses": 13,
        "games_played": 43,
        "win_rate": 69.77
      },
      "Brightwing": {
        "wins": 1,
        "losses": 1,
        "games_played": 2,
        "win_rate": 50
      },
      "Cassia": {
        "wins": 3,
        "losses": 4,
        "games_played": 7,
        "win_rate": 42.86
      },
      "Chen": {
        "wins": 1,
        "losses": 0,
        "games_played": 1,
        "win_rate": 100
      },
      "Deckard": {
        "wins": 1,
        "losses": 0,
        "games_played": 1,
        "win_rate": 100
      },
      "Diablo": {
        "wins": 1,
        "losses": 1,
        "games_played": 2,
        "win_rate": 50
      },
      "E.T.C.": {
        "wins": 1,
        "losses": 1,
        "games_played": 2,
        "win_rate": 50
      },
      "Falstad": {
        "wins": 2,
        "losses": 1,
        "games_played": 3,
        "win_rate": 66.67
      },
      "Garrosh": {
        "wins": 1,
        "losses": 5,
        "games_played": 6,
        "win_rate": 16.67
      },
      "Gul'dan": {
        "wins": 1,
        "losses": 3,
        "games_played": 4,
        "win_rate": 25
      },
      "Illidan": {
        "wins": 2,
        "losses": 1,
        "games_played": 3,
        "win_rate": 66.67
      },
      "Jaina": {
        "wins": 1,
        "losses": 0,
        "games_played": 1,
        "win_rate": 100
      },
      "Johanna": {
        "wins": 1,
        "losses": 0,
        "games_played": 1,
        "win_rate": 100
      },
      "Junkrat": {
        "wins": 6,
        "losses": 8,
        "games_played": 14,
        "win_rate": 42.86
      },
      "Kael'thas": {
        "wins": 11,
        "losses": 7,
        "games_played": 18,
        "win_rate": 61.11
      },
      "Kel'Thuzad": {
        "wins": 8,
        "losses": 3,
        "games_played": 11,
        "win_rate": 72.73
      },
      "Li-Ming": {
        "wins": 4,
        "losses": 2,
        "games_played": 6,
        "win_rate": 66.67
      },
      "L\u00facio": {
        "wins": 1,
        "losses": 4,
        "games_played": 5,
        "win_rate": 20
      },
      "Lunara": {
        "wins": 1,
        "losses": 0,
        "games_played": 1,
        "win_rate": 100
      },
      "Malfurion": {
        "wins": 1,
        "losses": 0,
        "games_played": 1,
        "win_rate": 100
      },
      "Medivh": {
        "wins": 0,
        "losses": 1,
        "games_played": 1,
        "win_rate": 0
      },
      "Mei": {
        "wins": 2,
        "losses": 1,
        "games_played": 3,
        "win_rate": 66.67
      },
      "Muradin": {
        "wins": 1,
        "losses": 3,
        "games_played": 4,
        "win_rate": 25
      },
      "Murky": {
        "wins": 0,
        "losses": 1,
        "games_played": 1,
        "win_rate": 0
      },
      "Nazeebo": {
        "wins": 6,
        "losses": 11,
        "games_played": 17,
        "win_rate": 35.29
      },
      "Qhira": {
        "wins": 1,
        "losses": 0,
        "games_played": 1,
        "win_rate": 100
      },
      "Ragnaros": {
        "wins": 1,
        "losses": 1,
        "games_played": 2,
        "win_rate": 50
      },
      "Raynor": {
        "wins": 1,
        "losses": 2,
        "games_played": 3,
        "win_rate": 33.33
      },
      "Rexxar": {
        "wins": 0,
        "losses": 1,
        "games_played": 1,
        "win_rate": 0
      },
      "Sgt. Hammer": {
        "wins": 2,
        "losses": 0,
        "games_played": 2,
        "win_rate": 100
      },
      "Stitches": {
        "wins": 4,
        "losses": 3,
        "games_played": 7,
        "win_rate": 57.14
      },
      "Stukov": {
        "wins": 1,
        "losses": 5,
        "games_played": 6,
        "win_rate": 16.67
      },
      "Sylvanas": {
        "wins": 1,
        "losses": 0,
        "games_played": 1,
        "win_rate": 100
      },
      "Tassadar": {
        "wins": 3,
        "losses": 3,
        "games_played": 6,
        "win_rate": 50
      },
      "The Butcher": {
        "wins": 1,
        "losses": 0,
        "games_played": 1,
        "win_rate": 100
      },
      "Tracer": {
        "wins": 4,
        "losses": 4,
        "games_played": 8,
        "win_rate": 50
      },
      "Tychus": {
        "wins": 1,
        "losses": 3,
        "games_played": 4,
        "win_rate": 25
      },
      "Valla": {
        "wins": 3,
        "losses": 1,
        "games_played": 4,
        "win_rate": 75
      },
      "Varian": {
        "wins": 1,
        "losses": 1,
        "games_played": 2,
        "win_rate": 50
      },
      "Zagara": {
        "wins": 0,
        "losses": 1,
        "games_played": 1,
        "win_rate": 0
      },
      "Zeratul": {
        "wins": 0,
        "losses": 1,
        "games_played": 1,
        "win_rate": 0
      },
      "Zul'jin": {
        "wins": 2,
        "losses": 0,
        "games_played": 2,
        "win_rate": 100
      }
    },
    "Towers of Doom": {
      "Ana": {
        "wins": 4,
        "losses": 6,
        "games_played": 10,
        "win_rate": 40
      },
      "Anub'arak": {
        "wins": 2,
        "losses": 0,
        "games_played": 2,
        "win_rate": 100
      },
      "Auriel": {
        "wins": 0,
        "losses": 1,
        "games_played": 1,
        "win_rate": 0
      },
      "Azmodan": {
        "wins": 20,
        "losses": 10,
        "games_played": 30,
        "win_rate": 66.67
      },
      "Brightwing": {
        "wins": 1,
        "losses": 2,
        "games_played": 3,
        "win_rate": 33.33
      },
      "Cassia": {
        "wins": 3,
        "losses": 5,
        "games_played": 8,
        "win_rate": 37.5
      },
      "Deckard": {
        "wins": 1,
        "losses": 1,
        "games_played": 2,
        "win_rate": 50
      },
      "Dehaka": {
        "wins": 0,
        "losses": 3,
        "games_played": 3,
        "win_rate": 0
      },
      "Diablo": {
        "wins": 1,
        "losses": 1,
        "games_played": 2,
        "win_rate": 50
      },
      "E.T.C.": {
        "wins": 1,
        "losses": 2,
        "games_played": 3,
        "win_rate": 33.33
      },
      "Falstad": {
        "wins": 2,
        "losses": 1,
        "games_played": 3,
        "win_rate": 66.67
      },
      "Garrosh": {
        "wins": 5,
        "losses": 5,
        "games_played": 10,
        "win_rate": 50
      },
      "Gazlowe": {
        "wins": 0,
        "losses": 1,
        "games_played": 1,
        "win_rate": 0
      },
      "Illidan": {
        "wins": 0,
        "losses": 1,
        "games_played": 1,
        "win_rate": 0
      },
      "Imperius": {
        "wins": 0,
        "losses": 2,
        "games_played": 2,
        "win_rate": 0
      },
      "Jaina": {
        "wins": 1,
        "losses": 0,
        "games_played": 1,
        "win_rate": 100
      },
      "Junkrat": {
        "wins": 1,
        "losses": 3,
        "games_played": 4,
        "win_rate": 25
      },
      "Kael'thas": {
        "wins": 1,
        "losses": 6,
        "games_played": 7,
        "win_rate": 14.29
      },
      "Kel'Thuzad": {
        "wins": 1,
        "losses": 0,
        "games_played": 1,
        "win_rate": 100
      },
      "Leoric": {
        "wins": 4,
        "losses": 2,
        "games_played": 6,
        "win_rate": 66.67
      },
      "Li Li": {
        "wins": 0,
        "losses": 1,
        "games_played": 1,
        "win_rate": 0
      },
      "L\u00facio": {
        "wins": 1,
        "losses": 2,
        "games_played": 3,
        "win_rate": 33.33
      },
      "Malfurion": {
        "wins": 0,
        "losses": 1,
        "games_played": 1,
        "win_rate": 0
      },
      "Medivh": {
        "wins": 2,
        "losses": 2,
        "games_played": 4,
        "win_rate": 50
      },
      "Mei": {
        "wins": 2,
        "losses": 0,
        "games_played": 2,
        "win_rate": 100
      },
      "Muradin": {
        "wins": 2,
        "losses": 1,
        "games_played": 3,
        "win_rate": 66.67
      },
      "Nazeebo": {
        "wins": 14,
        "losses": 15,
        "games_played": 29,
        "win_rate": 48.28
      },
      "Nova": {
        "wins": 4,
        "losses": 5,
        "games_played": 9,
        "win_rate": 44.44
      },
      "Raynor": {
        "wins": 8,
        "losses": 9,
        "games_played": 17,
        "win_rate": 47.06
      },
      "Sgt. Hammer": {
        "wins": 1,
        "losses": 0,
        "games_played": 1,
        "win_rate": 100
      },
      "Stitches": {
        "wins": 12,
        "losses": 5,
        "games_played": 17,
        "win_rate": 70.59
      },
      "Stukov": {
        "wins": 0,
        "losses": 4,
        "games_played": 4,
        "win_rate": 0
      },
      "Tassadar": {
        "wins": 0,
        "losses": 1,
        "games_played": 1,
        "win_rate": 0
      },
      "The Butcher": {
        "wins": 0,
        "losses": 2,
        "games_played": 2,
        "win_rate": 0
      },
      "Tracer": {
        "wins": 8,
        "losses": 15,
        "games_played": 23,
        "win_rate": 34.78
      },
      "Tychus": {
        "wins": 2,
        "losses": 2,
        "games_played": 4,
        "win_rate": 50
      },
      "Valla": {
        "wins": 4,
        "losses": 2,
        "games_played": 6,
        "win_rate": 66.67
      },
      "Varian": {
        "wins": 0,
        "losses": 3,
        "games_played": 3,
        "win_rate": 0
      },
      "Xul": {
        "wins": 2,
        "losses": 6,
        "games_played": 8,
        "win_rate": 25
      },
      "Zeratul": {
        "wins": 2,
        "losses": 0,
        "games_played": 2,
        "win_rate": 100
      },
      "Zul'jin": {
        "wins": 0,
        "losses": 1,
        "games_played": 1,
        "win_rate": 0
      }
    },
    "Warhead Junction": {
      "Ana": {
        "wins": 1,
        "losses": 1,
        "games_played": 2,
        "win_rate": 50
      },
      "Azmodan": {
        "wins": 2,
        "losses": 3,
        "games_played": 5,
        "win_rate": 40
      },
      "Brightwing": {
        "wins": 0,
        "losses": 1,
        "games_played": 1,
        "win_rate": 0
      },
      "Dehaka": {
        "wins": 1,
        "losses": 3,
        "games_played": 4,
        "win_rate": 25
      },
      "Diablo": {
        "wins": 0,
        "losses": 4,
        "games_played": 4,
        "win_rate": 0
      },
      "Garrosh": {
        "wins": 0,
        "losses": 4,
        "games_played": 4,
        "win_rate": 0
      },
      "Gazlowe": {
        "wins": 0,
        "losses": 1,
        "games_played": 1,
        "win_rate": 0
      },
      "Gul'dan": {
        "wins": 1,
        "losses": 0,
        "games_played": 1,
        "win_rate": 100
      },
      "Junkrat": {
        "wins": 0,
        "losses": 1,
        "games_played": 1,
        "win_rate": 0
      },
      "Kael'thas": {
        "wins": 1,
        "losses": 0,
        "games_played": 1,
        "win_rate": 100
      },
      "Kel'Thuzad": {
        "wins": 0,
        "losses": 2,
        "games_played": 2,
        "win_rate": 0
      },
      "Leoric": {
        "wins": 0,
        "losses": 1,
        "games_played": 1,
        "win_rate": 0
      },
      "Li-Ming": {
        "wins": 1,
        "losses": 0,
        "games_played": 1,
        "win_rate": 100
      },
      "L\u00facio": {
        "wins": 0,
        "losses": 1,
        "games_played": 1,
        "win_rate": 0
      },
      "Lunara": {
        "wins": 0,
        "losses": 1,
        "games_played": 1,
        "win_rate": 0
      },
      "Malfurion": {
        "wins": 1,
        "losses": 0,
        "games_played": 1,
        "win_rate": 100
      },
      "Medivh": {
        "wins": 1,
        "losses": 1,
        "games_played": 2,
        "win_rate": 50
      },
      "Muradin": {
        "wins": 0,
        "losses": 1,
        "games_played": 1,
        "win_rate": 0
      },
      "Nazeebo": {
        "wins": 3,
        "losses": 2,
        "games_played": 5,
        "win_rate": 60
      },
      "Nova": {
        "wins": 2,
        "losses": 0,
        "games_played": 2,
        "win_rate": 100
      },
      "Raynor": {
        "wins": 1,
        "losses": 0,
        "games_played": 1,
        "win_rate": 100
      },
      "Stitches": {
        "wins": 0,
        "losses": 1,
        "games_played": 1,
        "win_rate": 0
      },
      "Stukov": {
        "wins": 2,
        "losses": 4,
        "games_played": 6,
        "win_rate": 33.33
      },
      "Tassadar": {
        "wins": 1,
        "losses": 3,
        "games_played": 4,
        "win_rate": 25
      },
      "The Butcher": {
        "wins": 4,
        "losses": 2,
        "games_played": 6,
        "win_rate": 66.67
      },
      "Tracer": {
        "wins": 3,
        "losses": 2,
        "games_played": 5,
        "win_rate": 60
      },
      "Tychus": {
        "wins": 1,
        "losses": 3,
        "games_played": 4,
        "win_rate": 25
      },
      "Varian": {
        "wins": 0,
        "losses": 1,
        "games_played": 1,
        "win_rate": 0
      },
      "Xul": {
        "wins": 0,
        "losses": 1,
        "games_played": 1,
        "win_rate": 0
      }
    },
    "Hanamura Temple": {
      "Ana": {
        "wins": 3,
        "losses": 4,
        "games_played": 7,
        "win_rate": 42.86
      },
      "Anduin": {
        "wins": 1,
        "losses": 3,
        "games_played": 4,
        "win_rate": 25
      },
      "Artanis": {
        "wins": 0,
        "losses": 4,
        "games_played": 4,
        "win_rate": 0
      },
      "Azmodan": {
        "wins": 13,
        "losses": 10,
        "games_played": 23,
        "win_rate": 56.52
      },
      "Cassia": {
        "wins": 3,
        "losses": 2,
        "games_played": 5,
        "win_rate": 60
      },
      "Chen": {
        "wins": 0,
        "losses": 1,
        "games_played": 1,
        "win_rate": 0
      },
      "Diablo": {
        "wins": 3,
        "losses": 2,
        "games_played": 5,
        "win_rate": 60
      },
      "Garrosh": {
        "wins": 1,
        "losses": 1,
        "games_played": 2,
        "win_rate": 50
      },
      "Greymane": {
        "wins": 1,
        "losses": 0,
        "games_played": 1,
        "win_rate": 100
      },
      "Illidan": {
        "wins": 1,
        "losses": 0,
        "games_played": 1,
        "win_rate": 100
      },
      "Kael'thas": {
        "wins": 0,
        "losses": 2,
        "games_played": 2,
        "win_rate": 0
      },
      "Li-Ming": {
        "wins": 2,
        "losses": 7,
        "games_played": 9,
        "win_rate": 22.22
      },
      "L\u00facio": {
        "wins": 2,
        "losses": 4,
        "games_played": 6,
        "win_rate": 33.33
      },
      "Lunara": {
        "wins": 0,
        "losses": 3,
        "games_played": 3,
        "win_rate": 0
      },
      "Medivh": {
        "wins": 0,
        "losses": 1,
        "games_played": 1,
        "win_rate": 0
      },
      "Muradin": {
        "wins": 2,
        "losses": 2,
        "games_played": 4,
        "win_rate": 50
      },
      "Nazeebo": {
        "wins": 2,
        "losses": 3,
        "games_played": 5,
        "win_rate": 40
      },
      "Raynor": {
        "wins": 2,
        "losses": 2,
        "games_played": 4,
        "win_rate": 50
      },
      "Rexxar": {
        "wins": 2,
        "losses": 2,
        "games_played": 4,
        "win_rate": 50
      },
      "Stitches": {
        "wins": 8,
        "losses": 6,
        "games_played": 14,
        "win_rate": 57.14
      },
      "Stukov": {
        "wins": 1,
        "losses": 1,
        "games_played": 2,
        "win_rate": 50
      },
      "Tassadar": {
        "wins": 0,
        "losses": 3,
        "games_played": 3,
        "win_rate": 0
      },
      "The Butcher": {
        "wins": 1,
        "losses": 3,
        "games_played": 4,
        "win_rate": 25
      },
      "Tracer": {
        "wins": 10,
        "losses": 4,
        "games_played": 14,
        "win_rate": 71.43
      },
      "Varian": {
        "wins": 0,
        "losses": 1,
        "games_played": 1,
        "win_rate": 0
      }
    },
    "Blackheart's Bay": {
      "Junkrat": {
        "wins": 1,
        "losses": 0,
        "games_played": 1,
        "win_rate": 100
      },
      "Murky": {
        "wins": 0,
        "losses": 1,
        "games_played": 1,
        "win_rate": 0
      },
      "Nazeebo": {
        "wins": 2,
        "losses": 1,
        "games_played": 3,
        "win_rate": 66.67
      },
      "Stitches": {
        "wins": 1,
        "losses": 0,
        "games_played": 1,
        "win_rate": 100
      },
      "Varian": {
        "wins": 1,
        "losses": 0,
        "games_played": 1,
        "win_rate": 100
      }
    }
  }
}